<?xml version='1.0'?>
<ExamSession>
<ExamSessionDate>10/4/2019 2:25:54 PM</ExamSessionDate>
<Patient>
<FirstName>example2</FirstName>
<LastName>example2a</LastName>
<DateOfBirth>10/18/1965</DateOfBirth>
<Notes></Notes>
</Patient>
<PatientChecklist>
<Bruises>NO</Bruises>
<Rashes>NO</Rashes>
<Bulges>NO</Bulges>
<Indentations>NO</Indentations>
<Discharge>NO</Discharge>
<Marking>ONE - SEE INTAKE FORM</Marking>
<Thickening>NO</Thickening>
<Discoloration>NO</Discoloration>
<Lumps>NO</Lumps>
<NippleInv>NO</NippleInv>
<Trauma>SEE NOTE BELOW</Trauma>
<Concerns>NONE - SHE SUSPECTS THERE MAY BE A CHANGE IN SCORE DUE TO INJURY DESCRIBED BELOW</Concerns>
<AnythElse>SHE WAS PULLING WEEKS AND FELT SOMETHING RIP IN HER RIBCAGE WHEN SHE PULLED A SMALL TREE WITH ALL HER MIGHT. VERY PAINFUL. A FEW MONTHS AGO. FEELS LIKE SHE SEPARATED THE MUSCLE FROM THE RIB. PAINFUL FOR ABOUT A MONTH. GETS OCCASIONAL PAIN NOW. SEE INTAKE FORM
PATERNAL GRANDMOTHER DIED OF BREAST CANCER. GOT IT LATE IN LIFE AND WAS NOT TREATED. LIVED LONGER</AnythElse>
<Complaints>Routine follow-up thermal breast assessment</Complaints>
<HistoricalOverview></HistoricalOverview>
</PatientChecklist>
<ScannedForms>
<Image>patient_history_1.jpg</Image>
<Image>patient_history_2.jpg</Image>
<Image>patient_history_4.jpg</Image>
</ScannedForms>
<Exams>
<Exam>
<ExamTemplate>BreastExam</ExamTemplate>
<ExamCaption>Breast Scan</ExamCaption>
<ExamDirectory>BreastExam</ExamDirectory>
<ImageGroups>
<ImageGroup>
<name>BASELINE</name>
<row>1</row>
<Image><Sequence>1</Sequence><Caption>ANTERIOR</Caption><ImageFile>0101_baseline_anterior.jpg</ImageFile><Notes></Notes></Image>
<Image><Sequence>2</Sequence><Caption>OBLIQUE LEFT</Caption><ImageFile>0102_baseline_oblique left.jpg</ImageFile><Notes></Notes></Image>
<Image><Sequence>3</Sequence><Caption>OBLIQUE RIGHT</Caption><ImageFile>0103_baseline_oblique right.jpg</ImageFile><Notes></Notes></Image>
<Image><Sequence>4</Sequence><Caption>LATERAL LEFT</Caption><ImageFile>0104_baseline_lateral left.jpg</ImageFile><Notes></Notes></Image>
<Image><Sequence>5</Sequence><Caption>LATERAL RIGHT</Caption><ImageFile>0105_baseline_lateral right.jpg</ImageFile><Notes></Notes></Image>
<Image><Sequence>6</Sequence><Caption>INFERIOR VIEW</Caption><ImageFile>0106_baseline_inferior view.jpg</ImageFile><Notes></Notes></Image>
</ImageGroup>
<ImageGroup>
<name>FUNCTIONAL TEST</name>
<row>2</row>
<Image><Sequence>1</Sequence><Caption>ANTERIOR</Caption><ImageFile>0201_functional test_anterior.jpg</ImageFile><Notes></Notes></Image>
<Image><Sequence>2</Sequence><Caption>OBLIQUE LEFT</Caption><ImageFile>0202_functional test_oblique left.jpg</ImageFile><Notes></Notes></Image>
<Image><Sequence>3</Sequence><Caption>OBLIQUE RIGHT</Caption><ImageFile>0203_functional test_oblique right.jpg</ImageFile><Notes></Notes></Image>
<Image><Sequence>4</Sequence><Caption>LATERAL LEFT</Caption><ImageFile>0204_functional test_lateral left.jpg</ImageFile><Notes></Notes></Image>
<Image><Sequence>5</Sequence><Caption>LATERAL RIGHT</Caption><ImageFile>0205_functional test_lateral right.jpg</ImageFile><Notes></Notes></Image>
<Image><Sequence>6</Sequence><Caption>INFERIOR VIEW</Caption><ImageFile>0206_functional test_inferior view.jpg</ImageFile><Notes></Notes></Image>
</ImageGroup>
</ImageGroups>
</Exam>
</Exams>
</ExamSession>